isb_miner3-1.2.4.data/scripts/drug2opentargets
isb_miner3-1.2.4.data/scripts/gene2opentargets
isb_miner3-1.2.4.data/scripts/miner3-causalinference
isb_miner3-1.2.4.data/scripts/miner3-coexpr
isb_miner3-1.2.4.data/scripts/miner3-mechinf
isb_miner3-1.2.4.data/scripts/miner3-riskpredict
isb_miner3-1.2.4.data/scripts/miner3-subtypes
isb_miner3-1.2.4.data/scripts/miner3-survival
miner/__init__.py
miner/bcmembers.py
miner/causal_inference.py
miner/coexpression.py
miner/mechinf.py
miner/miner.py
miner/miner_working_frequency_matrix.py
miner/opentargets.py
miner/progressbar.py
miner/subtypes.py
miner/util.py
miner/validation.py
miner/data/all_tfs_to_motifs.pkl
miner/data/epigenes.txt
miner/data/identifier_mappings.txt
miner/data/network_dictionaries/GO_bio.pkl
miner/data/network_dictionaries/GO_bio_reciprocal.pkl
miner/data/network_dictionaries/chea_reciprocal.pkl
miner/data/network_dictionaries/chea_seq.pkl
miner/data/network_dictionaries/hallmarks.pkl
miner/data/network_dictionaries/hallmarks_reciprocal.pkl
miner/data/network_dictionaries/mirna.pkl
miner/data/network_dictionaries/mirna_reciprocal.pkl
miner/data/network_dictionaries/motif_to_primary_tf.pkl
miner/data/network_dictionaries/pathways.pkl
miner/data/network_dictionaries/pathways_reciprocal.pkl
miner/data/network_dictionaries/primary_tf_to_motif.pkl
miner/data/network_dictionaries/protein_interactions.pkl
miner/data/network_dictionaries/reciprocal_tfbsdb_ensembl.pkl
miner/data/network_dictionaries/tf2genes1.json
miner/data/network_dictionaries/tf2genes2.json
miner/data/network_dictionaries/tf2genes_jsonified.zip
miner/data/network_dictionaries/tfbsdb2_all_tfs_to_motifs.pkl
miner/data/network_dictionaries/tfbsdb2_genes_to_tf.pkl
miner/data/network_dictionaries/tfbsdb2_tf_to_genes.pkl
miner/data/network_dictionaries/tfbsdb_genes_to_tf.pkl
miner/data/network_dictionaries/tfbsdb_tf_to_genes.pkl
isb_miner3-1.2.4.dist-info/LICENSE
isb_miner3-1.2.4.dist-info/METADATA
isb_miner3-1.2.4.dist-info/WHEEL
isb_miner3-1.2.4.dist-info/top_level.txt
isb_miner3-1.2.4.dist-info/RECORD
