Metadata-Version: 2.1
Name: isb_miner3
Version: 1.2.4
Summary: MINER analysis tools
Home-page: https://github.com/baliga-lab/miner3
Author: Matt Wall
Author-email: mwall@systemsbiology.org
Classifier: Development Status :: 5 - Production/Stable
Classifier: Environment :: Console
Classifier: Intended Audience :: Science/Research
Classifier: Natural Language :: English
Classifier: License :: OSI Approved :: GNU General Public License v3 or later (GPLv3+)
Classifier: Operating System :: OS Independent
Classifier: Programming Language :: Python
Classifier: Programming Language :: Python :: 2
Classifier: Programming Language :: Python :: 2.7
Classifier: Programming Language :: Python
Classifier: Programming Language :: Python :: 3
Classifier: Programming Language :: Python :: 3.6
Classifier: Topic :: Scientific/Engineering :: Bio-Informatics
Classifier: Topic :: Software Development :: Libraries :: Python Modules
License-File: LICENSE
Requires-Dist: numpy>=1.22.0
Requires-Dist: scipy>=1.8.0
Requires-Dist: pandas>=2.0.0
Requires-Dist: scikit-learn>=1.1.3
Requires-Dist: lifelines>=0.27.4
Requires-Dist: matplotlib>=3.6.0
Requires-Dist: seaborn>=0.12.0
Requires-Dist: mygene>=3.2.2
Requires-Dist: requests_toolbelt>=1.0.0
Requires-Dist: pydot>=2.0.0
Requires-Dist: graphviz>=0.20.1
Requires-Dist: gql>=3.4.0
Requires-Dist: chembl_webresource_client>=0.10.8
Requires-Dist: tqdm>=4.64.0
